tnreason/__init__.py
tnreason/application/__init__.py
tnreason/application/categoricals_to_cores.py
tnreason/application/cnf_to_cores.py
tnreason/application/data_to_cores.py
tnreason/application/deductive.py
tnreason/application/distributions.py
tnreason/application/formulas_to_cores.py
tnreason/application/grafting.py
tnreason/application/inductive.py
tnreason/application/knowledge_visualization.py
tnreason/application/neurons_to_cores.py
tnreason/application/script_transform.py
tnreason/application/storage.py
tnreason/engine/__init__.py
tnreason/engine/contraction_handling.py
tnreason/engine/core_base.py
tnreason/engine/core_creation.py
tnreason/engine/engine_visualization.py
tnreason/engine/polynomial_handling.py
tnreason/engine/subscript_creation.py
tnreason/engine/workload_to_gurobi.py
tnreason/engine/workload_to_numpy.py
tnreason/engine/workload_to_pandas.py
tnreason/engine/workload_to_pgmpy.py
tnreason/engine/workload_to_tensorflow.py
tnreason/engine/workload_to_tentris.py
tnreason/engine/workload_to_torch.py
tnreason/reasoning/__init__.py
tnreason/reasoning/alternating_least_squares.py
tnreason/reasoning/binary_propagation.py
tnreason/reasoning/constraint_propagation.py
tnreason/reasoning/energy_based_algorithms.py
tnreason/reasoning/forward_sampling.py
tnreason/reasoning/message_passing.py
tnreason/reasoning/optimization_handling.py
tnreason/reasoning/sampling_base.py
tnreason/reasoning/sampling_handling.py
tnreason/reasoning/variational_inference.py
tnreason/representation/__init__.py
tnreason/representation/basisPlus_calculus.py
tnreason/representation/basis_calculus.py
tnreason/representation/ca_network.py
tnreason/representation/coordinate_calculus.py
tnreason/representation/features.py
tnreason/representation/suffixes.py
tnreason/representation/workload_to_sparqlwrapper.py
tnreason-2.0.0.dist-info/.DS_Store
tnreason-2.0.0.dist-info/LICENSE
tnreason-2.0.0.dist-info/METADATA
tnreason-2.0.0.dist-info/WHEEL
tnreason-2.0.0.dist-info/top_level.txt
tnreason-2.0.0.dist-info/RECORD
