Metadata-Version: 2.1
Name: tnreason
Version: 2.0.0
Summary: A package for reasoning based on tensor networks
Home-page: https://github.com/EnexaProject/enexa-tensor-reasoning
Author: Alex Goessmann
Author-email: alex.goessmann@web.de
License: AGPL-3.0
Keywords: markov logic networks,tensor networks,explainable AI,gibbs sampling,inductive logic programming,neuro-symbolic AI
Classifier: Programming Language :: Python :: 3.8
Classifier: License :: OSI Approved :: GNU Affero General Public License v3 or later (AGPLv3+)
Classifier: Operating System :: OS Independent
Classifier: Topic :: Scientific/Engineering :: Artificial Intelligence
Requires-Python: >=3
License-File: LICENSE
Requires-Dist: numpy >=1.17
Requires-Dist: pandas >=1.0.0
Requires-Dist: gurobipy
Requires-Dist: SPARQLWrapper
Requires-Dist: networkx
Requires-Dist: pyyaml
Requires-Dist: sortedcontainers
